{
	"type": "ItemTurret",
	"name": "俎力",
	"health": 12000,
	"armor": -15,
	"size": 6,
	"reload": 300,
	"range": 700,
	"recoilTime": 120,
	"recoil": 6,
	"cooldownTime": 40,
	"shake": 8,
	"warmupMaintainTime": 60,
	"shoot": {
		"type": "ShootAlternate",
		"barrels": 2,
		"spread": 14,
		"shots": 3,
		"shotDelay": 10
	},
	"recoils": 2,
	"drawer": {
		"type": "DrawTurret",
		"parts": [
			{
				"type": "RegionPart",
				"mirror": false,
				"suffix": "-后",
				"under": true,
				"moveY": -12.25,
				"progress": "warmup",
				"heatProgress": "recoil",
				"heatColor": "FF7055"
			},
			{
				"type": "RegionPart",
				"mirror": false,
				"under": true,
				"suffix": "-前",
				"moveY": 16
			},
			{
				"type": "HaloPart",
				"shapeRotation": 5,
				"y": 44,
				"sides": 4,
				"shapes": 1,
				"rotateSpeed": 0.2,
				"color": "76D081",
				"layer": 110,
				"tri": false,
				"hollow": true,
				"stroke": 0,
				"strokeTo": 1.7,
				"radius": 0,
				"radiusTo": 12
			},
			{
				"type": "HaloPart",
				"y": 38,
				"sides": 4,
				"shapes": 1,
				"rotateSpeed": 0.2,
				"color": "76D081",
				"layer": 110,
				"tri": false,
				"hollow": true,
				"stroke": 0,
				"strokeTo": 1.9,
				"radius": 0,
				"radiusTo": 14
			},
			{
				"type": "HaloPart",
				"shapeRotation": -5,
				"y": 30,
				"sides": 4,
				"shapes": 1,
				"rotateSpeed": 0.2,
				"color": "76D081",
				"layer": 110,
				"tri": false,
				"hollow": true,
				"stroke": 0,
				"strokeTo": 2.1,
				"radius": 0,
				"radiusTo": 16
			},
			{
				"type": "RegionPart",
				"mirror": true,
				"under": true,
				"suffix": "-1",
				"moveX": -8,
				"moveY": 8
			},
		]
	},
	"consumes": {
		"power": 180,
		"liquid": "纳米流体/2"
	},
	"liquidCapacity": 300,
	"shootSound": "release",
	"rotateSpeed": 3,
	"ammoPerShot": 6,
	"consumeAmmoOnce": false,
	"ammoTypes": {
		"纳米核": {
			"type": "BasicBulletType",
			"ammoMultiplier": 1,
			"height": 25,
			"width": 25,
			"hitSize": 8,
			"shrinkY": 0,
			"weaveScale": 8,
			"weaveMag": 1,
			"absorbable": false,
			"homingDelay": 40,
			"homingPower": 0.08,
			"homingRange": 80,
			"damage": 33,
			"splashDamageRadius": 60,
			"splashDamage": 60,
			"status": "拆解",
			"sprite": "large-orb",
			"frontColor": "FFFFFF",
			"backColor": "97FFA8",
			"trailLength": 46,
			"trailWidth": 2,
			"trailColor": "97FFA8",
			"speed": 15,
			"drag": 0.03,
			"knockback": 20,
			"lifetime": 120,
			"hitEffect": {
				"type": "MultiEffect",
				"effects": [
					{
						"type": "ParticleEffect",
						"particles": 7,
						"sizeFrom": 10,
						"sizeTo": 0,
						"length": 40,
						"baseLength": 9,
						"lifetime": 60,
						"interp": "circleOut",
						"sizeInterp": "circleOut",
						"colorFrom": "97FFA8",
						"colorTo": "97FFA8A8"
					},
					{
						"type": "ParticleEffect",
						"particles": 16,
						"line": true,
						"strokeFrom": 3,
						"strokeTo": 0,
						"lenFrom": 20,
						"lenTo": 0,
						"length": 60,
						"baseLength": 9,
						"lifetime": 60,
						"interp": "circleOut",
						"sizeInterp": "circleOut",
						"colorFrom": "97FFA8",
						"colorTo": "97FFA8"
					},
					{
						"type": "WaveEffect",
						"lifetime": 60,
						"sizeFrom": 2,
						"sizeTo": 60,
						"strokeFrom": 7,
						"strokeTo": 0,
						"interp": "circleOut",
						"colorFrom": "97FFA8",
						"colorTo": "97FFA8"
					}
				]
			},
			"smokeEffect": "none",
			"hitSound": "plasmaboom",
			"bulletInterval": 1.5,
			"intervalBullets": 2,
			"intervalBullet": {
				"type": "BasicBulletType",
				"width": 8,
				"height": 10,
				"frontColor": "FFFFFF",
				"backColor": "97FFA8",
				"absorbable": false,
				"collidesTeam": true,
				"healAmount": 10,
				"trailLength": 20,
				"trailWidth": 1,
				"trailColor": "97FFA8",
				"homingDelay": 5,
				"homingPower": 0.1,
				"homingRange": 200,
				"speed": 18,
				"drag": 0.03,
				"lifetime": 12,
				"damage": 66,
				"knockback": 12,
				"hitColor": "97FFA8",
				"hitEffect": {
					"type": "MultiEffect",
					"effects": [
						"hitBulletColor",
						{
							"type": "ParticleEffect",
							"particles": 5,
							"strokeFrom": 3,
							"strokeTo": 0,
							"lenFrom": 18,
							"lenTo": 0,
							"line": true,
							"length": 40,
							"baseLength": 0,
							"lifetime": 20,
							"sizeInterp": "circleOut",
							"colorFrom": "97FFA8",
							"colorTo": "97FFA8",
							"cone": 30
						}
					]
				},
				"despawnEffect": {
					"type": "WaveEffect",
					"strokeFrom": 3,
					"strokeTo": 0,
					"lifetime": 30,
					"sizeFrom": 0,
					"sizeTo": 8,
					"interp": "circleOut"
				},
				"status": "干扰",
				"statusDuration": 8,
				"fragOnHit": false,
				"fragBullets": 1,
				"fragVelocityMin": 1,
				"fragBullet": {
					"type": "MissileBulletType",
					"width": 8,
					"height": 10,
					"frontColor": "FFFFFF",
					"backColor": "97FFA8",
					"absorbable": false,
					"collidesTeam": true,
					"healAmount": 10,
					"trailLength": 20,
					"trailWidth": 1,
					"trailColor": "97FFA8",
					"homingDelay": 5,
					"homingPower": 1,
					"homingRange": 200,
					"speed": 8,
					"lifetime": 25,
					"damage": 36,
					"hitColor": "97FFA8",
					"hitEffect": {
						"type": "ExplosionEffect",
						"lifetime": 28,
						"waveStroke": 5,
						"waveLife": 22,
						"waveRadBase": 7,
						"waveColor": "97FFA8",
						"waveRad": 38,
						"smokes": 6,
						"smokeColor": "FFFFFF",
						"sparkColor": "97FFA8",
						"sparks": 6,
						"sparkRad": 35,
						"sparkStroke": 1.5,
						"sparkLen": 7
					},
					"status": "electrified",
					"statusDuration": 12
				}
			},
			"fragOnHit": false,
			"fragBullets": 30,
			"fragLifeMin": 0.3,
			"fragBullet": {
				"type": "MissileBulletType",
				"width": 8,
				"height": 10,
				"frontColor": "FFFFFF",
				"backColor": "97FFA8",
				"absorbable": false,
				"collidesTeam": true,
				"healAmount": 10,
				"trailLength": 20,
				"trailWidth": 1,
				"trailColor": "97FFA8",
				"homingDelay": 5,
				"homingPower": 0.1,
				"homingRange": 200,
				"speed": 8,
				"lifetime": 32,
				"damage": 36,
				"splashDamageRadius": 35,
				"splashDamage": 36,
				"hitColor": "97FFA8",
				"hitEffect": {
					"type": "ExplosionEffect",
					"lifetime": 28,
					"waveStroke": 5,
					"waveLife": 22,
					"waveRadBase": 7,
					"waveColor": "97FFA8",
					"waveRad": 38,
					"smokes": 6,
					"smokeColor": "FFFFFF",
					"sparkColor": "97FFA8",
					"sparks": 6,
					"sparkRad": 35,
					"sparkStroke": 1.5,
					"sparkLen": 7
				},
				"status": "干扰",
				"statusDuration": 10
			}
		}
	},
	"requirements": [],
	"category": "turret",
	"research": {
		"research": "纳米风暴",
		"objectives": [
			{
				"type": "SectorComplete",
				"preset": "第五战区"
			}
		]
	}
}