{
	"name": "饱和火力",
	"displayName":"Saturation firepower",
	"author":"RA2",
	"version":"3.1.5",
	"minGameVersion":"146",
	"repo":"RA2EXE/Saturation-Firepower",
	"hideInBrowser": false,
	"description":"QQ群：181108928\n或者前往Github查看火力最新状态\n饱和火力服务器保持常开，请装载最新模组进入\n[green[]]———————————————[white[]]\n战前须知：在宁开始挑战火力的高难度战役前，请务必做好[red[]]备份工作！\n[white[]]mod不对玩家因自己的错误操作导致的不可挽回后果负责！\n小贴士：自定义先试试以免打不过\n[green[]]———————————————[white[]]
3.1.5更新：
——————地图类——————
▲新地图-战争集成工业区
溢裂要塞-磁爆区域重构
——————炮台类——————
气旋-裂位能弹药视觉效果修复
死诏-特效适配
//漫游-爆炸范围降低
//光阴-缩短近炸引信距离-爆炸伤害提高
——————单位类——————
玄冥-降低主炮强度
侵蚀-输出量增加
——————电力类——————
磁爆反应堆-贴图重做-限制为地编建筑
——————物流类——————
硅钢传送带-不再绝缘
塑钢传送带-可以越过水面-造价增加
交叉器-可以越过水面
"
}
